mq/__init__.py
mq/v1/__init__.py
mq/v1/mq_pb2.py
mq/v1/mq_pb2_grpc.py
togomq_grpc-0.1.11.dist-info/licenses/LICENSE
togomq_grpc-0.1.11.dist-info/METADATA
togomq_grpc-0.1.11.dist-info/WHEEL
togomq_grpc-0.1.11.dist-info/top_level.txt
togomq_grpc-0.1.11.dist-info/RECORD
