Metadata-Version: 2.4
Name: togomq-grpc
Version: 0.1.11
Summary: Auto-generated gRPC Python client for TogoMQ
Home-page: https://github.com/TogoMQ/togomq-grpc-python
Author: Enter Pages Pro Ltd
Author-email: Enter Pages Pro Ltd <dev@enterpages.co.uk>
Project-URL: Homepage, https://togomq.io
Project-URL: Bug Tracker, https://github.com/TogoMQ/togomq-grpc-python/issues
Project-URL: Documentation, https://togomq.io
Project-URL: Source Code, https://github.com/TogoMQ/togomq-grpc-python
Classifier: Development Status :: 4 - Beta
Classifier: Intended Audience :: Developers
Classifier: License :: OSI Approved :: MIT License
Classifier: Operating System :: OS Independent
Classifier: Programming Language :: Python :: 3
Classifier: Programming Language :: Python :: 3.9
Classifier: Programming Language :: Python :: 3.10
Classifier: Programming Language :: Python :: 3.11
Classifier: Programming Language :: Python :: 3.12
Classifier: Topic :: Software Development :: Libraries :: Python Modules
Requires-Python: >=3.9
License-File: LICENSE
Requires-Dist: grpcio>=1.60.0
Requires-Dist: protobuf>=5.29.0
Provides-Extra: dev
Requires-Dist: grpcio-tools>=1.60.0; extra == "dev"
Dynamic: author
Dynamic: home-page
Dynamic: license-file
Dynamic: requires-python
